futhark_data/__init__.py
futhark_data-1.0.3.dist-info/LICENSE
futhark_data-1.0.3.dist-info/METADATA
futhark_data-1.0.3.dist-info/WHEEL
futhark_data-1.0.3.dist-info/top_level.txt
futhark_data-1.0.3.dist-info/zip-safe
futhark_data-1.0.3.dist-info/RECORD
