Metadata-Version: 2.1
Name: futhark-data
Version: 1.0.3
Summary: Reading and writing Futhark data files
Home-page: https://github.com/diku-dk/futhark-data-python
Author: Troels Henriksen
Author-email: athas@sigkill.dk
License: ISC
Platform: UNKNOWN
Classifier: Programming Language :: Python :: 3
Classifier: License :: OSI Approved :: ISC License (ISCL)
Classifier: Operating System :: OS Independent
Requires-Python: >=3.9
License-File: LICENSE
Requires-Dist: numpy
